{
    "_request_time_gmt": "2016-11-04 05:15:59", 
    "rate": {
        "limit": 5000, 
        "remaining": 5000, 
        "reset": 1478240159
    }, 
    "resources": {
        "core": {
            "limit": 5000, 
            "remaining": 5000, 
            "reset": 1478240159
        }, 
        "graphql": {
            "limit": 200, 
            "remaining": 200, 
            "reset": 1478240159
        }, 
        "search": {
            "limit": 30, 
            "remaining": 30, 
            "reset": 1478236619
        }
    }
}